LICENSE
MANIFEST.in
README.md
requirements.txt
setup.py
src/django_postgres_tweaks.egg-info/PKG-INFO
src/django_postgres_tweaks.egg-info/SOURCES.txt
src/django_postgres_tweaks.egg-info/dependency_links.txt
src/django_postgres_tweaks.egg-info/requires.txt
src/django_postgres_tweaks.egg-info/top_level.txt
src/postgres_utils/__init__.py
src/postgres_utils/apps.py
src/postgres_utils/functions.py
src/postgres_utils/lookups.py