Metadata-Version: 2.1
Name: django-postgres-tweaks
Version: 0.1.2
Summary: Special PostgreSQL lookups and functions for Django apps
Home-page: https://github.com/Canned-Django/django-postgres-utils
Author: Andreas Hasenkopf
Author-email: andreas@hasenkopf.xyz
License: MIT
Project-URL: Documentation, https://canned-djangodjango-postgres-utils.readthedocs.io/
Platform: UNKNOWN
Classifier: Development Status :: 5 - Production/Stable
Classifier: Environment :: Web Environment
Classifier: Framework :: Django
Classifier: Framework :: Django :: 2.2
Classifier: Framework :: Django :: 3.0
Classifier: Intended Audience :: Developers
Classifier: License :: OSI Approved :: MIT License
Classifier: Operating System :: OS Independent
Classifier: Programming Language :: Python :: 3.4
Classifier: Programming Language :: Python :: 3.5
Classifier: Programming Language :: Python :: 3.6
Classifier: Programming Language :: Python :: 3.7
Classifier: Programming Language :: Python :: 3.8
Classifier: Programming Language :: Python :: 3.9
Classifier: Topic :: Database
